apache_airflow_dragdrop_plugin/plugin.py
apache_airflow_dragdrop_plugin/static/assets/index-0977d9bf.css
apache_airflow_dragdrop_plugin/static/assets/index-134f50d9.js
apache_airflow_dragdrop_plugin/static/assets/index-a8582e13.css
apache_airflow_dragdrop_plugin/static/assets/index-faaebae2.js
apache_airflow_dragdrop_plugin/templates/index.html
apache_airflow_dragdrop_plugin-1.1.4.dist-info/LICENSE
apache_airflow_dragdrop_plugin-1.1.4.dist-info/METADATA
apache_airflow_dragdrop_plugin-1.1.4.dist-info/WHEEL
apache_airflow_dragdrop_plugin-1.1.4.dist-info/entry_points.txt
apache_airflow_dragdrop_plugin-1.1.4.dist-info/top_level.txt
apache_airflow_dragdrop_plugin-1.1.4.dist-info/RECORD
