Metadata-Version: 2.2
Name: apache-airflow-dragdrop-plugin
Version: 1.1.4
Summary: A custom Apache Airflow plugin to integrate a React UI
Home-page: https://github.com/datainteg/apache-airflow-dragdrop-plugin
Author: Akshay Thakare
Author-email: thakarea686@gmail.com
License: Apache License, Version 2.0
Classifier: Programming Language :: Python :: 3
Classifier: Framework :: Apache Airflow
Classifier: Operating System :: OS Independent
Requires-Python: >=3
License-File: LICENSE
Requires-Dist: apache-airflow>=2.0.0
Requires-Dist: flask
Dynamic: author
Dynamic: author-email
Dynamic: classifier
Dynamic: description
Dynamic: description-content-type
Dynamic: home-page
Dynamic: license
Dynamic: requires-dist
Dynamic: requires-python
Dynamic: summary
